pysparketl/__init__.py
pysparketl/dataframes.py
pysparketl-0.0.3.dist-info/LICENSE
pysparketl-0.0.3.dist-info/METADATA
pysparketl-0.0.3.dist-info/WHEEL
pysparketl-0.0.3.dist-info/top_level.txt
pysparketl-0.0.3.dist-info/RECORD
