Metadata-Version: 2.1
Name: pysparketl
Version: 0.0.3
Summary: This project performs pyspark operations on dataframes, currently for unnesting shallow or deeply nested json data.
Home-page: https://github.com/murtada91/Pckg---Pypsark-Json-Flattener
Author: Murtada Ahmed
Author-email: murtadaosama@gmail.com
Project-URL: Bug Tracker, https://github.com/murtada91/Pckg---Pypsark-Json-Flattener/issues
Classifier: Programming Language :: Python :: 3
Classifier: License :: OSI Approved :: MIT License
Classifier: Operating System :: OS Independent
Requires-Python: >=3.6
License-File: LICENSE
